{"is_source_file": false, "format": "", "description": "", "external_files": [], "external_methods": [], "published": [], "classes": [], "methods": [], "calls": [], "search-terms": [], "state": 2, "file_id": 42, "knowledge_revision": 171, "git_revision": "cb1725278595076f89bdff718c235dd382b960a2", "hash": "b6425687357b125f1e21a22649cba71f", "format-version": 4, "code-base-name": "DatabaseContainer", "filename": "BackendContainer/pyproject.toml", "revision_history": [{"171": "cb1725278595076f89bdff718c235dd382b960a2"}]}