{"is_source_file": true, "format": "TypeScript (TSX)", "description": "A React component for listing and managing jobs with real-time updates, sorting, filtering, and UI elements. Implements fetching job data from an API, real-time WebSocket updates, and UI rendering.", "external_files": ["../services/api", "../utils/realtime", "./ui/Skeleton", "./ui/EmptyState", "./ui/ErrorBanner", "./ui/Button", "./ui/Badge", "../utils/cn"], "external_methods": ["api().get", "useSSE", "getSSEUrl"], "published": ["JobList"], "classes": [], "methods": [{"name": "fetchJobs", "description": "Fetches job list data from the API and updates the component state."}, {"name": "getStatusBadge", "description": "Returns a Badge component with the appropriate status variant based on job status."}, {"name": "toggleSort", "description": "Switches sorting order for a specified sort key."}], "calls": ["api().get", "useSSE", "getSSEUrl"], "search-terms": ["React job list component", "real-time job updates", "TypeScript job management", "UI job filtering and sorting", "Job status badges"], "state": 2, "file_id": 28, "knowledge_revision": 235, "git_revision": "582897b7558ba85b38c1b792149d883cc2c6b59e", "revision_history": [{"67": "6590bfa06afc3693b6cdd76a1680213beba9d0d9"}, {"186": "be4492d7a5c565b42d01595db152d8b53f8224b1"}, {"235": "582897b7558ba85b38c1b792149d883cc2c6b59e"}], "ctags": [], "hash": "0f203eafc24dba923adb97490377aee6", "format-version": 4, "code-base-name": "DatabaseContainer", "filename": "FrontendContainer/src/components/JobList.tsx"}